dv_utils/__init__.py
dv_utils/__main__.py
dv_utils/client.py
dv_utils/connectors/__init__.py
dv_utils/connectors/connector.py
dv_utils/connectors/simple_file.py
dv_utils/listener.py
dv_utils/log_utils.py
dv_utils/process.py
dv_utils/redis.py
dv_utils/settings.py
dv_utils-0.2.3.dist-info/METADATA
dv_utils-0.2.3.dist-info/WHEEL
dv_utils-0.2.3.dist-info/RECORD
